uidgenerator/__init__.py
uidgenerator/constants.py
uidgenerator/datacenterworkid.py
uidgenerator/usnowflake.py
aimframe_uidgenerator-1.0.3.dist-info/LICENSE
aimframe_uidgenerator-1.0.3.dist-info/METADATA
aimframe_uidgenerator-1.0.3.dist-info/WHEEL
aimframe_uidgenerator-1.0.3.dist-info/top_level.txt
aimframe_uidgenerator-1.0.3.dist-info/RECORD
