Metadata-Version: 2.1
Name: aimframe_uidgenerator
Version: 1.0.3
Summary: 雪花id生成器-解决时钟回拨问题
Author: worldofchu
Author-email: worldofchu@163.com
Requires-Python: >=3.6
License-File: LICENSE
